{
    "name": "scene",
    "objects": [
        {
            "type": "MESH",
            "name": "Block.008",
            "file_name": "Block",
            "ModelFileType": "obj",
            "DrawType": "Instancing",
            "InstancingObjName": "Map",
            "transform": {
                "translate": [
                    75.73153686523438,
                    0.0,
                    30.542856216430664
                ],
                "rotate": [
                    0.0,
                    -0.0,
                    0.0
                ],
                "scale": [
                    10.0,
                    1.0,
                    3.5
                ]
            },
            "collider": {
                "type": "Box",
                "center": [
                    0.0,
                    0.0,
                    0.0
                ],
                "size": [
                    2.0,
                    2.0,
                    2.0
                ]
            }
        },
        {
            "type": "MESH",
            "name": "BreakBlockMap",
            "file_name": "BreakBlock",
            "ModelFileType": "obj",
            "DrawType": "Normal",
            "transform": {
                "translate": [
                    -9.0,
                    0.0,
                    16.5
                ],
                "rotate": [
                    0.0,
                    -0.0,
                    0.0
                ],
                "scale": [
                    9.5,
                    1.0,
                    9.5
                ]
            },
            "collider": {
                "type": "Box",
                "center": [
                    0.0,
                    0.0,
                    0.0
                ],
                "size": [
                    2.0,
                    2.0,
                    2.0
                ]
            }
        },
        {
            "type": "MESH",
            "name": "Player",
            "file_name": "Human",
            "ModelFileType": "gltf",
            "DrawType": "Normal",
            "transform": {
                "translate": [
                    -67.73775482177734,
                    0.0,
                    10.0
                ],
                "rotate": [
                    0.0,
                    -0.0,
                    0.0
                ],
                "scale": [
                    1.0,
                    1.0,
                    1.0
                ]
            },
            "collider": {
                "type": "Box",
                "center": [
                    0.0,
                    0.0,
                    0.0
                ],
                "size": [
                    2.0,
                    2.0,
                    4.0
                ]
            }
        },
        {
            "type": "MESH",
            "name": "Goal",
            "file_name": "Goal",
            "ModelFileType": "obj",
            "DrawType": "Normal",
            "transform": {
                "translate": [
                    79.27192687988281,
                    0.0,
                    36.909908294677734
                ],
                "rotate": [
                    0.0,
                    -0.0,
                    0.0
                ],
                "scale": [
                    1.0,
                    1.0,
                    1.0
                ]
            },
            "collider": {
                "type": "Box",
                "center": [
                    0.0,
                    0.0,
                    0.0
                ],
                "size": [
                    2.0,
                    2.0,
                    2.0
                ]
            },
            "children": [
                {
                    "type": "MESH",
                    "name": "GoalBack",
                    "file_name": "GoalBack",
                    "ModelFileType": "obj",
                    "DrawType": "Normal",
                    "transform": {
                        "translate": [
                            0.0,
                            0.0,
                            0.0
                        ],
                        "rotate": [
                            0.0,
                            -0.0,
                            0.0
                        ],
                        "scale": [
                            2.0,
                            2.0,
                            2.0
                        ]
                    }
                }
            ]
        },
        {
            "type": "MESH",
            "name": "WarpGate",
            "file_name": "WarpGate",
            "ModelFileType": "obj",
            "DrawType": "Normal",
            "paramFileNames": {
                "File 0": "stage_1/stage1_1_1"
            },
            "transform": {
                "translate": [
                    15.357666015625,
                    0.0,
                    4.545066833496094
                ],
                "rotate": [
                    0.0,
                    -0.0,
                    0.0
                ],
                "scale": [
                    1.0,
                    1.0,
                    1.0
                ]
            },
            "collider": {
                "type": "Box",
                "center": [
                    0.0,
                    0.0,
                    0.0
                ],
                "size": [
                    2.0,
                    2.0,
                    2.0
                ]
            }
        },
        {
            "type": "MESH",
            "name": "WarpGate.001",
            "file_name": "WarpGate",
            "ModelFileType": "obj",
            "DrawType": "Normal",
            "paramFileNames": {
                "File 0": "stage_1/WarpGate_2"
            },
            "transform": {
                "translate": [
                    15.357666015625,
                    0.0,
                    38.545066833496094
                ],
                "rotate": [
                    0.0,
                    -0.0,
                    0.0
                ],
                "scale": [
                    1.0,
                    1.0,
                    1.0
                ]
            },
            "collider": {
                "type": "Box",
                "center": [
                    0.0,
                    0.0,
                    0.0
                ],
                "size": [
                    2.0,
                    2.0,
                    2.0
                ]
            }
        },
        {
            "type": "MESH",
            "name": "Lava",
            "file_name": "LavaPlane",
            "ModelFileType": "obj",
            "DrawType": "Normal",
            "transform": {
                "translate": [
                    0.0,
                    0.0,
                    -15.576512336730957
                ],
                "rotate": [
                    0.0,
                    -0.0,
                    0.0
                ],
                "scale": [
                    256.0,
                    256.0,
                    256.0
                ]
            }
        },
        {
            "type": "MESH",
            "name": "PlayerGun",
            "file_name": "PlayerGun",
            "ModelFileType": "obj",
            "DrawType": "Normal",
            "transform": {
                "translate": [
                    -67.56848907470703,
                    3.3508048057556152,
                    10.86166000366211
                ],
                "rotate": [
                    0.0,
                    -0.0,
                    0.0
                ],
                "scale": [
                    1.0,
                    1.0,
                    1.0
                ]
            }
        },
        {
            "type": "MESH",
            "name": "smallRock",
            "file_name": "smallRock",
            "ModelFileType": "obj",
            "DrawType": "Normal",
            "transform": {
                "translate": [
                    -9.56491756439209,
                    141.36395263671875,
                    -12.626368522644043
                ],
                "rotate": [
                    0.0,
                    -0.0,
                    0.0
                ],
                "scale": [
                    2.0,
                    2.0,
                    2.0
                ]
            }
        },
        {
            "type": "MESH",
            "name": "smallRock.001",
            "file_name": "smallRock",
            "ModelFileType": "obj",
            "DrawType": "Normal",
            "transform": {
                "translate": [
                    -29.750558853149414,
                    65.6171646118164,
                    -12.626368522644043
                ],
                "rotate": [
                    0.0,
                    -0.0,
                    0.0
                ],
                "scale": [
                    4.0,
                    4.0,
                    4.0
                ]
            }
        },
        {
            "type": "MESH",
            "name": "smallRock.002",
            "file_name": "smallRock",
            "ModelFileType": "obj",
            "DrawType": "Normal",
            "transform": {
                "translate": [
                    23.01106071472168,
                    65.6171646118164,
                    -12.626368522644043
                ],
                "rotate": [
                    0.0,
                    -0.0,
                    0.0
                ],
                "scale": [
                    4.0,
                    4.0,
                    4.0
                ]
            }
        },
        {
            "type": "MESH",
            "name": "FlatRock",
            "file_name": "FlatRock",
            "ModelFileType": "obj",
            "DrawType": "Normal",
            "transform": {
                "translate": [
                    -0.491851806640625,
                    292.93310546875,
                    0.0
                ],
                "rotate": [
                    0.0,
                    -0.0,
                    0.0
                ],
                "scale": [
                    40.0,
                    40.0,
                    40.0
                ]
            }
        },
        {
            "type": "MESH",
            "name": "GunEnemyBarrel.001",
            "file_name": "GunEnemyBarrel",
            "ModelFileType": "obj",
            "DrawType": "Normal",
            "transform": {
                "translate": [
                    0.0,
                    1.1100000143051147,
                    30.004867553710938
                ],
                "rotate": [
                    0.0,
                    -0.0,
                    0.0
                ],
                "scale": [
                    1.0,
                    1.0,
                    1.0
                ]
            }
        },
        {
            "type": "MESH",
            "name": "FlatRock.001",
            "file_name": "FlatRock",
            "ModelFileType": "obj",
            "DrawType": "Normal",
            "transform": {
                "translate": [
                    138.61061096191406,
                    156.22412109375,
                    0.0
                ],
                "rotate": [
                    0.0,
                    0.0,
                    -59.77857208251953
                ],
                "scale": [
                    39.999996185302734,
                    39.999996185302734,
                    40.0
                ]
            }
        },
        {
            "type": "MESH",
            "name": "FlatRock.002",
            "file_name": "FlatRock",
            "ModelFileType": "obj",
            "DrawType": "Normal",
            "transform": {
                "translate": [
                    76.77031707763672,
                    235.2974853515625,
                    24.184154510498047
                ],
                "rotate": [
                    -56.34930419921875,
                    15.824295043945312,
                    2.4749114513397217
                ],
                "scale": [
                    40.0,
                    40.0,
                    40.0
                ]
            }
        },
        {
            "type": "MESH",
            "name": "FlatRock.003",
            "file_name": "FlatRock",
            "ModelFileType": "obj",
            "DrawType": "Normal",
            "transform": {
                "translate": [
                    -107.11499786376953,
                    187.89419555664062,
                    24.184154510498047
                ],
                "rotate": [
                    -56.34928512573242,
                    15.824288368225098,
                    54.425819396972656
                ],
                "scale": [
                    40.0,
                    40.0,
                    40.0
                ]
            }
        },
        {
            "type": "MESH",
            "name": "FlatRock.004",
            "file_name": "FlatRock",
            "ModelFileType": "obj",
            "DrawType": "Normal",
            "transform": {
                "translate": [
                    -229.3517608642578,
                    187.89419555664062,
                    -17.897319793701172
                ],
                "rotate": [
                    -56.34929656982422,
                    15.824295043945312,
                    83.17274475097656
                ],
                "scale": [
                    39.999996185302734,
                    40.0,
                    40.0
                ]
            }
        },
        {
            "type": "MESH",
            "name": "FlatRock.005",
            "file_name": "FlatRock",
            "ModelFileType": "obj",
            "DrawType": "Normal",
            "transform": {
                "translate": [
                    195.84487915039062,
                    182.30857849121094,
                    24.184154510498047
                ],
                "rotate": [
                    -34.98954772949219,
                    -15.36042308807373,
                    -53.193382263183594
                ],
                "scale": [
                    40.0,
                    40.0,
                    40.0
                ]
            }
        },
        {
            "type": "MESH",
            "name": "FlatRock.006",
            "file_name": "FlatRock",
            "ModelFileType": "obj",
            "DrawType": "Normal",
            "transform": {
                "translate": [
                    -229.3517608642578,
                    26.600814819335938,
                    -17.897319793701172
                ],
                "rotate": [
                    -73.04010009765625,
                    22.21875762939453,
                    78.35961151123047
                ],
                "scale": [
                    39.999996185302734,
                    40.0,
                    40.0
                ]
            }
        },
        {
            "type": "MESH",
            "name": "FlatRock.007",
            "file_name": "FlatRock",
            "ModelFileType": "obj",
            "DrawType": "Normal",
            "transform": {
                "translate": [
                    -211.4626007080078,
                    116.02888488769531,
                    50.62700271606445
                ],
                "rotate": [
                    -64.32703399658203,
                    23.627952575683594,
                    81.75916290283203
                ],
                "scale": [
                    39.999996185302734,
                    40.0,
                    40.0
                ]
            }
        },
        {
            "type": "MESH",
            "name": "smallRock.003",
            "file_name": "smallRock",
            "ModelFileType": "obj",
            "DrawType": "Normal",
            "transform": {
                "translate": [
                    -37.183807373046875,
                    -35.32072448730469,
                    -12.626368522644043
                ],
                "rotate": [
                    0.0,
                    -0.0,
                    0.0
                ],
                "scale": [
                    4.0,
                    4.0,
                    4.0
                ]
            }
        },
        {
            "type": "MESH",
            "name": "Block",
            "file_name": "Block",
            "ModelFileType": "obj",
            "DrawType": "Instancing",
            "InstancingObjName": "Map",
            "transform": {
                "translate": [
                    -34.0,
                    0.0,
                    -20.0
                ],
                "rotate": [
                    0.0,
                    -0.0,
                    0.0
                ],
                "scale": [
                    60.0,
                    1.0,
                    20.0
                ]
            },
            "collider": {
                "type": "Box",
                "center": [
                    0.0,
                    0.0,
                    0.0
                ],
                "size": [
                    2.0,
                    2.0,
                    2.0
                ]
            }
        },
        {
            "type": "MESH",
            "name": "Block.001",
            "file_name": "Block",
            "ModelFileType": "obj",
            "DrawType": "Instancing",
            "InstancingObjName": "Map",
            "transform": {
                "translate": [
                    -44.18395233154297,
                    0.0,
                    8.0
                ],
                "rotate": [
                    0.0,
                    -0.0,
                    0.0
                ],
                "scale": [
                    10.0,
                    1.0,
                    1.0
                ]
            },
            "collider": {
                "type": "Box",
                "center": [
                    0.0,
                    0.0,
                    0.0
                ],
                "size": [
                    2.0,
                    2.0,
                    2.0
                ]
            }
        },
        {
            "type": "MESH",
            "name": "Block.002",
            "file_name": "Block",
            "ModelFileType": "obj",
            "DrawType": "Instancing",
            "InstancingObjName": "Map",
            "transform": {
                "translate": [
                    -87.0,
                    0.0,
                    20.0
                ],
                "rotate": [
                    0.0,
                    -0.0,
                    0.0
                ],
                "scale": [
                    6.877225875854492,
                    1.0,
                    20.0
                ]
            },
            "collider": {
                "type": "Box",
                "center": [
                    0.0,
                    0.0,
                    0.0
                ],
                "size": [
                    2.0,
                    2.0,
                    2.0
                ]
            }
        },
        {
            "type": "MESH",
            "name": "Block.003",
            "file_name": "Block",
            "ModelFileType": "obj",
            "DrawType": "Instancing",
            "InstancingObjName": "Map",
            "transform": {
                "translate": [
                    23.0,
                    0.0,
                    13.0
                ],
                "rotate": [
                    0.0,
                    -0.0,
                    0.0
                ],
                "scale": [
                    3.0,
                    1.0,
                    13.0
                ]
            },
            "collider": {
                "type": "Box",
                "center": [
                    0.0,
                    0.0,
                    0.0
                ],
                "size": [
                    2.0,
                    2.0,
                    2.0
                ]
            }
        },
        {
            "type": "MESH",
            "name": "Block.004",
            "file_name": "Block",
            "ModelFileType": "obj",
            "DrawType": "Instancing",
            "InstancingObjName": "Map",
            "transform": {
                "translate": [
                    -53.17266082763672,
                    0.0,
                    3.5
                ],
                "rotate": [
                    0.0,
                    -0.0,
                    0.0
                ],
                "scale": [
                    1.0,
                    1.0,
                    3.5
                ]
            },
            "collider": {
                "type": "Box",
                "center": [
                    0.0,
                    0.0,
                    0.0
                ],
                "size": [
                    2.0,
                    2.0,
                    2.0
                ]
            }
        },
        {
            "type": "MESH",
            "name": "Block.005",
            "file_name": "Block",
            "ModelFileType": "obj",
            "DrawType": "Instancing",
            "InstancingObjName": "Map",
            "transform": {
                "translate": [
                    -9.0,
                    0.0,
                    3.5
                ],
                "rotate": [
                    0.0,
                    -0.0,
                    0.0
                ],
                "scale": [
                    10.0,
                    1.0,
                    3.5
                ]
            },
            "collider": {
                "type": "Box",
                "center": [
                    0.0,
                    0.0,
                    0.0
                ],
                "size": [
                    2.0,
                    2.0,
                    2.0
                ]
            }
        },
        {
            "type": "MESH",
            "name": "Block.006",
            "file_name": "Block",
            "ModelFileType": "obj",
            "DrawType": "Instancing",
            "InstancingObjName": "Map",
            "transform": {
                "translate": [
                    0.0,
                    0.0,
                    29.5
                ],
                "rotate": [
                    0.0,
                    -0.0,
                    0.0
                ],
                "scale": [
                    26.0,
                    1.0,
                    3.5
                ]
            },
            "collider": {
                "type": "Box",
                "center": [
                    0.0,
                    0.0,
                    0.0
                ],
                "size": [
                    2.0,
                    2.0,
                    2.0
                ]
            }
        },
        {
            "type": "MESH",
            "name": "Block.007",
            "file_name": "Block",
            "ModelFileType": "obj",
            "DrawType": "Instancing",
            "InstancingObjName": "Map",
            "transform": {
                "translate": [
                    46.0,
                    0.0,
                    26.0
                ],
                "rotate": [
                    0.0,
                    -0.0,
                    0.0
                ],
                "scale": [
                    20.0,
                    1.0,
                    3.5
                ]
            },
            "collider": {
                "type": "Box",
                "center": [
                    0.0,
                    0.0,
                    0.0
                ],
                "size": [
                    2.0,
                    2.0,
                    2.0
                ]
            }
        },
        {
            "type": "MESH",
            "name": "EnemyWalk",
            "file_name": "EnemyWalk",
            "ModelFileType": "obj",
            "DrawType": "Normal",
            "transform": {
                "translate": [
                    -43.89952087402344,
                    0.0,
                    2.4983596801757812
                ],
                "rotate": [
                    0.0,
                    -0.0,
                    0.0
                ],
                "scale": [
                    2.0,
                    2.0,
                    2.0
                ]
            },
            "collider": {
                "type": "Box",
                "center": [
                    0.0,
                    0.0,
                    0.0
                ],
                "size": [
                    2.0,
                    2.0,
                    2.0
                ]
            }
        },
        {
            "type": "CAMERA",
            "name": "PlayerCamera",
            "transform": {
                "translate": [
                    5.849818706512451,
                    -32.0,
                    7.017513275146484
                ],
                "rotate": [
                    90.00000762939453,
                    -0.0,
                    0.0
                ],
                "scale": [
                    1.0,
                    1.0,
                    1.0
                ]
            }
        },
        {
            "type": "CAMERA",
            "name": "StartCamera",
            "paramFileNames": {
                "File 0": "Stage_1_0"
            },
            "transform": {
                "translate": [
                    0.0,
                    -120.0,
                    64.0
                ],
                "rotate": [
                    90.00000762939453,
                    -0.0,
                    0.0
                ],
                "scale": [
                    1.0,
                    1.0,
                    1.0
                ]
            }
        },
        {
            "type": "MESH",
            "name": "Tower",
            "file_name": "Tower",
            "ModelFileType": "obj",
            "DrawType": "Instancing",
            "InstancingObjName": "Tower",
            "transform": {
                "translate": [
                    -35.331695556640625,
                    198.5014190673828,
                    -12.47998046875
                ],
                "rotate": [
                    0.0,
                    -0.0,
                    0.0
                ],
                "scale": [
                    15.0,
                    15.0,
                    15.0
                ]
            },
            "collider": {
                "type": "Box",
                "center": [
                    0.0,
                    0.0,
                    0.0
                ],
                "size": [
                    2.0,
                    2.0,
                    2.0
                ]
            }
        },
        {
            "type": "MESH",
            "name": "Tower.001",
            "file_name": "Tower",
            "ModelFileType": "obj",
            "DrawType": "Instancing",
            "InstancingObjName": "Tower",
            "transform": {
                "translate": [
                    92.69062805175781,
                    61.663238525390625,
                    -20.545814514160156
                ],
                "rotate": [
                    0.0,
                    -0.0,
                    0.0
                ],
                "scale": [
                    7.5,
                    7.5,
                    7.5
                ]
            },
            "collider": {
                "type": "Box",
                "center": [
                    0.0,
                    0.0,
                    0.0
                ],
                "size": [
                    2.0,
                    2.0,
                    2.0
                ]
            }
        },
        {
            "type": "MESH",
            "name": "Tower.002",
            "file_name": "Tower",
            "ModelFileType": "obj",
            "DrawType": "Instancing",
            "InstancingObjName": "Tower",
            "transform": {
                "translate": [
                    11.578819274902344,
                    139.70068359375,
                    -20.545814514160156
                ],
                "rotate": [
                    0.0,
                    -0.0,
                    0.0
                ],
                "scale": [
                    10.5,
                    10.5,
                    10.5
                ]
            },
            "collider": {
                "type": "Box",
                "center": [
                    0.0,
                    0.0,
                    0.0
                ],
                "size": [
                    2.0,
                    2.0,
                    2.0
                ]
            }
        },
        {
            "type": "MESH",
            "name": "Tower.003",
            "file_name": "Tower",
            "ModelFileType": "obj",
            "DrawType": "Instancing",
            "InstancingObjName": "Tower",
            "transform": {
                "translate": [
                    170.369873046875,
                    73.75874328613281,
                    -20.545814514160156
                ],
                "rotate": [
                    0.0,
                    -0.0,
                    0.0
                ],
                "scale": [
                    7.5,
                    7.5,
                    7.5
                ]
            },
            "collider": {
                "type": "Box",
                "center": [
                    0.0,
                    0.0,
                    0.0
                ],
                "size": [
                    2.0,
                    2.0,
                    2.0
                ]
            }
        },
        {
            "type": "MESH",
            "name": "Tower.004",
            "file_name": "Tower",
            "ModelFileType": "obj",
            "DrawType": "Instancing",
            "InstancingObjName": "Tower",
            "transform": {
                "translate": [
                    56.50749969482422,
                    141.72634887695312,
                    -20.545814514160156
                ],
                "rotate": [
                    0.0,
                    -0.0,
                    0.0
                ],
                "scale": [
                    3.75,
                    3.75,
                    3.75
                ]
            },
            "collider": {
                "type": "Box",
                "center": [
                    0.0,
                    0.0,
                    0.0
                ],
                "size": [
                    2.0,
                    2.0,
                    2.0
                ]
            }
        },
        {
            "type": "MESH",
            "name": "Tower.005",
            "file_name": "Tower",
            "ModelFileType": "obj",
            "DrawType": "Instancing",
            "InstancingObjName": "Tower",
            "transform": {
                "translate": [
                    -125.20140075683594,
                    147.7939453125,
                    -12.47998046875
                ],
                "rotate": [
                    0.0,
                    -0.0,
                    0.0
                ],
                "scale": [
                    12.0,
                    12.0,
                    12.0
                ]
            },
            "collider": {
                "type": "Box",
                "center": [
                    0.0,
                    0.0,
                    0.0
                ],
                "size": [
                    2.0,
                    2.0,
                    2.0
                ]
            }
        },
        {
            "type": "MESH",
            "name": "Tower.006",
            "file_name": "Tower",
            "ModelFileType": "obj",
            "DrawType": "Instancing",
            "InstancingObjName": "Tower",
            "transform": {
                "translate": [
                    -76.84286499023438,
                    139.70068359375,
                    -20.545814514160156
                ],
                "rotate": [
                    0.0,
                    -0.0,
                    0.0
                ],
                "scale": [
                    7.5,
                    7.5,
                    7.5
                ]
            },
            "collider": {
                "type": "Box",
                "center": [
                    0.0,
                    0.0,
                    0.0
                ],
                "size": [
                    2.0,
                    2.0,
                    2.0
                ]
            }
        },
        {
            "type": "MESH",
            "name": "Tower.007",
            "file_name": "Tower",
            "ModelFileType": "obj",
            "DrawType": "Instancing",
            "InstancingObjName": "Tower",
            "transform": {
                "translate": [
                    102.86676025390625,
                    147.7939453125,
                    -12.47998046875
                ],
                "rotate": [
                    0.0,
                    -0.0,
                    0.0
                ],
                "scale": [
                    15.0,
                    15.0,
                    15.0
                ]
            },
            "collider": {
                "type": "Box",
                "center": [
                    0.0,
                    0.0,
                    0.0
                ],
                "size": [
                    2.0,
                    2.0,
                    2.0
                ]
            }
        },
        {
            "type": "MESH",
            "name": "Tower.008",
            "file_name": "Tower",
            "ModelFileType": "obj",
            "DrawType": "Instancing",
            "InstancingObjName": "Tower",
            "transform": {
                "translate": [
                    -227.36355590820312,
                    58.439422607421875,
                    -12.47998046875
                ],
                "rotate": [
                    0.0,
                    -0.0,
                    119.72737121582031
                ],
                "scale": [
                    15.0,
                    15.0,
                    15.0
                ]
            },
            "collider": {
                "type": "Box",
                "center": [
                    0.0,
                    0.0,
                    0.0
                ],
                "size": [
                    2.0,
                    2.0,
                    2.0
                ]
            }
        },
        {
            "type": "MESH",
            "name": "Tower.009",
            "file_name": "Tower",
            "ModelFileType": "obj",
            "DrawType": "Instancing",
            "InstancingObjName": "Tower",
            "transform": {
                "translate": [
                    -131.22219848632812,
                    -93.60626220703125,
                    -20.545814514160156
                ],
                "rotate": [
                    0.0,
                    -0.0,
                    119.72737121582031
                ],
                "scale": [
                    7.5,
                    7.5,
                    7.5
                ]
            },
            "collider": {
                "type": "Box",
                "center": [
                    0.0,
                    0.0,
                    0.0
                ],
                "size": [
                    2.0,
                    2.0,
                    2.0
                ]
            }
        },
        {
            "type": "MESH",
            "name": "Tower.010",
            "file_name": "Tower",
            "ModelFileType": "obj",
            "DrawType": "Instancing",
            "InstancingObjName": "Tower",
            "transform": {
                "translate": [
                    -114.27063751220703,
                    -212.65577697753906,
                    -12.47998046875
                ],
                "rotate": [
                    0.0,
                    -0.0,
                    119.72737121582031
                ],
                "scale": [
                    12.0,
                    12.0,
                    12.0
                ]
            },
            "collider": {
                "type": "Box",
                "center": [
                    0.0,
                    0.0,
                    0.0
                ],
                "size": [
                    2.0,
                    2.0,
                    2.0
                ]
            }
        },
        {
            "type": "MESH",
            "name": "Tower.011",
            "file_name": "Tower",
            "ModelFileType": "obj",
            "DrawType": "Instancing",
            "InstancingObjName": "Tower",
            "transform": {
                "translate": [
                    -199.10617065429688,
                    21.190048217773438,
                    -20.545814514160156
                ],
                "rotate": [
                    0.0,
                    -0.0,
                    119.72737121582031
                ],
                "scale": [
                    3.75,
                    3.75,
                    3.75
                ]
            },
            "collider": {
                "type": "Box",
                "center": [
                    0.0,
                    0.0,
                    0.0
                ],
                "size": [
                    2.0,
                    2.0,
                    2.0
                ]
            }
        },
        {
            "type": "MESH",
            "name": "Tower.012",
            "file_name": "Tower",
            "ModelFileType": "obj",
            "DrawType": "Instancing",
            "InstancingObjName": "Tower",
            "transform": {
                "translate": [
                    -196.54476928710938,
                    153.77085876464844,
                    -20.545814514160156
                ],
                "rotate": [
                    0.0,
                    -0.0,
                    119.72737121582031
                ],
                "scale": [
                    7.5,
                    7.5,
                    7.5
                ]
            },
            "collider": {
                "type": "Box",
                "center": [
                    0.0,
                    0.0,
                    0.0
                ],
                "size": [
                    2.0,
                    2.0,
                    2.0
                ]
            }
        },
        {
            "type": "MESH",
            "name": "Tower.014",
            "file_name": "Tower",
            "ModelFileType": "obj",
            "DrawType": "Instancing",
            "InstancingObjName": "Tower",
            "transform": {
                "translate": [
                    -147.52203369140625,
                    92.31243896484375,
                    -20.545814514160156
                ],
                "rotate": [
                    0.0,
                    -0.0,
                    119.72737121582031
                ],
                "scale": [
                    7.5,
                    7.5,
                    7.5
                ]
            },
            "collider": {
                "type": "Box",
                "center": [
                    0.0,
                    0.0,
                    0.0
                ],
                "size": [
                    2.0,
                    2.0,
                    2.0
                ]
            }
        },
        {
            "type": "MESH",
            "name": "Tower.015",
            "file_name": "Tower",
            "ModelFileType": "obj",
            "DrawType": "Instancing",
            "InstancingObjName": "Tower",
            "transform": {
                "translate": [
                    -202.86874389648438,
                    -86.71588134765625,
                    -12.47998046875
                ],
                "rotate": [
                    0.0,
                    -0.0,
                    119.72737121582031
                ],
                "scale": [
                    15.0,
                    15.0,
                    15.0
                ]
            },
            "collider": {
                "type": "Box",
                "center": [
                    0.0,
                    0.0,
                    0.0
                ],
                "size": [
                    2.0,
                    2.0,
                    2.0
                ]
            }
        },
        {
            "type": "MESH",
            "name": "Tower.016",
            "file_name": "Tower",
            "ModelFileType": "obj",
            "DrawType": "Instancing",
            "InstancingObjName": "Tower",
            "transform": {
                "translate": [
                    203.39053344726562,
                    -86.71588134765625,
                    -12.47998046875
                ],
                "rotate": [
                    0.0,
                    -180.0,
                    60.27266311645508
                ],
                "scale": [
                    -15.000000953674316,
                    -15.000000953674316,
                    -15.0
                ]
            },
            "collider": {
                "type": "Box",
                "center": [
                    0.0,
                    0.0,
                    0.0
                ],
                "size": [
                    2.0,
                    2.0,
                    2.0
                ]
            }
        },
        {
            "type": "MESH",
            "name": "Tower.017",
            "file_name": "Tower",
            "ModelFileType": "obj",
            "DrawType": "Instancing",
            "InstancingObjName": "Tower",
            "transform": {
                "translate": [
                    148.0438232421875,
                    92.31243896484375,
                    -20.545814514160156
                ],
                "rotate": [
                    0.0,
                    -180.0,
                    60.27266311645508
                ],
                "scale": [
                    -7.500000476837158,
                    -7.500000476837158,
                    -7.5
                ]
            },
            "collider": {
                "type": "Box",
                "center": [
                    0.0,
                    0.0,
                    0.0
                ],
                "size": [
                    2.0,
                    2.0,
                    2.0
                ]
            }
        },
        {
            "type": "MESH",
            "name": "Tower.018",
            "file_name": "Tower",
            "ModelFileType": "obj",
            "DrawType": "Instancing",
            "InstancingObjName": "Tower",
            "transform": {
                "translate": [
                    175.58993530273438,
                    -16.821311950683594,
                    -20.545814514160156
                ],
                "rotate": [
                    0.0,
                    -180.0,
                    60.27266311645508
                ],
                "scale": [
                    -10.500000953674316,
                    -10.500000953674316,
                    -10.5
                ]
            },
            "collider": {
                "type": "Box",
                "center": [
                    0.0,
                    0.0,
                    0.0
                ],
                "size": [
                    2.0,
                    2.0,
                    2.0
                ]
            }
        },
        {
            "type": "MESH",
            "name": "Tower.019",
            "file_name": "Tower",
            "ModelFileType": "obj",
            "DrawType": "Instancing",
            "InstancingObjName": "Tower",
            "transform": {
                "translate": [
                    197.06655883789062,
                    153.77085876464844,
                    -20.545814514160156
                ],
                "rotate": [
                    0.0,
                    -180.0,
                    60.27266311645508
                ],
                "scale": [
                    -7.500000476837158,
                    -7.500000476837158,
                    -7.5
                ]
            },
            "collider": {
                "type": "Box",
                "center": [
                    0.0,
                    0.0,
                    0.0
                ],
                "size": [
                    2.0,
                    2.0,
                    2.0
                ]
            }
        },
        {
            "type": "MESH",
            "name": "Tower.020",
            "file_name": "Tower",
            "ModelFileType": "obj",
            "DrawType": "Instancing",
            "InstancingObjName": "Tower",
            "transform": {
                "translate": [
                    199.62796020507812,
                    21.190048217773438,
                    -20.545814514160156
                ],
                "rotate": [
                    0.0,
                    -180.0,
                    60.27266311645508
                ],
                "scale": [
                    -3.750000238418579,
                    -3.750000238418579,
                    -3.75
                ]
            },
            "collider": {
                "type": "Box",
                "center": [
                    0.0,
                    0.0,
                    0.0
                ],
                "size": [
                    2.0,
                    2.0,
                    2.0
                ]
            }
        },
        {
            "type": "MESH",
            "name": "Tower.021",
            "file_name": "Tower",
            "ModelFileType": "obj",
            "DrawType": "Instancing",
            "InstancingObjName": "Tower",
            "transform": {
                "translate": [
                    114.79241943359375,
                    -139.61380004882812,
                    -12.47998046875
                ],
                "rotate": [
                    0.0,
                    -180.0,
                    60.27266311645508
                ],
                "scale": [
                    -12.0,
                    -12.0,
                    -12.0
                ]
            },
            "collider": {
                "type": "Box",
                "center": [
                    0.0,
                    0.0,
                    0.0
                ],
                "size": [
                    2.0,
                    2.0,
                    2.0
                ]
            }
        },
        {
            "type": "MESH",
            "name": "Tower.022",
            "file_name": "Tower",
            "ModelFileType": "obj",
            "DrawType": "Instancing",
            "InstancingObjName": "Tower",
            "transform": {
                "translate": [
                    131.74398803710938,
                    -93.60626220703125,
                    -20.545814514160156
                ],
                "rotate": [
                    0.0,
                    -180.0,
                    60.27266311645508
                ],
                "scale": [
                    -7.500000476837158,
                    -7.500000476837158,
                    -7.5
                ]
            },
            "collider": {
                "type": "Box",
                "center": [
                    0.0,
                    0.0,
                    0.0
                ],
                "size": [
                    2.0,
                    2.0,
                    2.0
                ]
            }
        },
        {
            "type": "MESH",
            "name": "Tower.023",
            "file_name": "Tower",
            "ModelFileType": "obj",
            "DrawType": "Instancing",
            "InstancingObjName": "Tower",
            "transform": {
                "translate": [
                    227.88534545898438,
                    58.439422607421875,
                    -12.47998046875
                ],
                "rotate": [
                    0.0,
                    -180.0,
                    60.27266311645508
                ],
                "scale": [
                    -15.000000953674316,
                    -15.000000953674316,
                    -15.0
                ]
            },
            "collider": {
                "type": "Box",
                "center": [
                    0.0,
                    0.0,
                    0.0
                ],
                "size": [
                    2.0,
                    2.0,
                    2.0
                ]
            }
        },
        {
            "type": "MESH",
            "name": "WarpRoot",
            "file_name": "WarpRoot",
            "ModelFileType": "obj",
            "DrawType": "Instancing",
            "InstancingObjName": "WarpRoot",
            "transform": {
                "translate": [
                    15.126625061035156,
                    2.9799644947052,
                    4.545070648193359
                ],
                "rotate": [
                    0.0,
                    -0.0,
                    -179.99998474121094
                ],
                "scale": [
                    1.0,
                    1.0,
                    1.0
                ]
            }
        },
        {
            "type": "MESH",
            "name": "WarpRoot.001",
            "file_name": "WarpRoot",
            "ModelFileType": "obj",
            "DrawType": "Instancing",
            "InstancingObjName": "WarpRoot",
            "transform": {
                "translate": [
                    15.126625061035156,
                    7.979964256286621,
                    4.545070648193359
                ],
                "rotate": [
                    0.0,
                    -0.0,
                    -179.99998474121094
                ],
                "scale": [
                    1.0,
                    1.0,
                    1.0
                ]
            }
        },
        {
            "type": "MESH",
            "name": "WarpHole",
            "file_name": "WarpHole",
            "ModelFileType": "obj",
            "DrawType": "Normal",
            "transform": {
                "translate": [
                    15.357666015625,
                    0.0,
                    4.545066833496094
                ],
                "rotate": [
                    0.0,
                    -0.0,
                    0.0
                ],
                "scale": [
                    1.0,
                    1.0,
                    1.0
                ]
            }
        },
        {
            "type": "MESH",
            "name": "WarpHole.001",
            "file_name": "WarpHole",
            "ModelFileType": "obj",
            "DrawType": "Normal",
            "transform": {
                "translate": [
                    15.357666015625,
                    0.0,
                    38.545066833496094
                ],
                "rotate": [
                    0.0,
                    -0.0,
                    0.0
                ],
                "scale": [
                    1.0,
                    1.0,
                    1.0
                ]
            }
        },
        {
            "type": "MESH",
            "name": "WarpRoot.002",
            "file_name": "WarpRoot",
            "ModelFileType": "obj",
            "DrawType": "Instancing",
            "InstancingObjName": "WarpRoot",
            "transform": {
                "translate": [
                    15.126625061035156,
                    12.479964256286621,
                    9.045066833496094
                ],
                "rotate": [
                    90.00000762939453,
                    5.757417654607411e-13,
                    -179.99998474121094
                ],
                "scale": [
                    1.0,
                    1.0,
                    1.0
                ]
            }
        },
        {
            "type": "MESH",
            "name": "WarpRoot.003",
            "file_name": "WarpRoot",
            "ModelFileType": "obj",
            "DrawType": "Instancing",
            "InstancingObjName": "WarpRoot",
            "transform": {
                "translate": [
                    15.126625061035156,
                    12.479964256286621,
                    14.045066833496094
                ],
                "rotate": [
                    90.00000762939453,
                    5.757417654607411e-13,
                    -179.99998474121094
                ],
                "scale": [
                    1.0,
                    1.0,
                    1.0
                ]
            }
        },
        {
            "type": "MESH",
            "name": "WarpRoot.004",
            "file_name": "WarpRoot",
            "ModelFileType": "obj",
            "DrawType": "Instancing",
            "InstancingObjName": "WarpRoot",
            "transform": {
                "translate": [
                    15.126625061035156,
                    12.479964256286621,
                    19.045066833496094
                ],
                "rotate": [
                    90.00000762939453,
                    5.757417654607411e-13,
                    -179.99998474121094
                ],
                "scale": [
                    1.0,
                    1.0,
                    1.0
                ]
            }
        },
        {
            "type": "MESH",
            "name": "WarpRoot.005",
            "file_name": "WarpRoot",
            "ModelFileType": "obj",
            "DrawType": "Instancing",
            "InstancingObjName": "WarpRoot",
            "transform": {
                "translate": [
                    15.126625061035156,
                    12.479964256286621,
                    24.045066833496094
                ],
                "rotate": [
                    90.00000762939453,
                    5.757417654607411e-13,
                    -179.99998474121094
                ],
                "scale": [
                    1.0,
                    1.0,
                    1.0
                ]
            }
        },
        {
            "type": "MESH",
            "name": "WarpRoot.006",
            "file_name": "WarpRoot",
            "ModelFileType": "obj",
            "DrawType": "Instancing",
            "InstancingObjName": "WarpRoot",
            "transform": {
                "translate": [
                    15.126625061035156,
                    12.479964256286621,
                    29.045066833496094
                ],
                "rotate": [
                    90.00000762939453,
                    5.757417654607411e-13,
                    -179.99998474121094
                ],
                "scale": [
                    1.0,
                    1.0,
                    1.0
                ]
            }
        },
        {
            "type": "MESH",
            "name": "WarpRoot.007",
            "file_name": "WarpRoot",
            "ModelFileType": "obj",
            "DrawType": "Instancing",
            "InstancingObjName": "WarpRoot",
            "transform": {
                "translate": [
                    15.126625061035156,
                    12.479964256286621,
                    34.045066833496094
                ],
                "rotate": [
                    90.00000762939453,
                    5.757417654607411e-13,
                    -179.99998474121094
                ],
                "scale": [
                    1.0,
                    1.0,
                    1.0
                ]
            }
        },
        {
            "type": "MESH",
            "name": "WarpRootConnector.001",
            "file_name": "WarpRootConnector",
            "ModelFileType": "obj",
            "DrawType": "Instancing",
            "InstancingObjName": "WarpConnector",
            "transform": {
                "translate": [
                    15.126625061035156,
                    11.979964256286621,
                    38.045066833496094
                ],
                "rotate": [
                    -90.00000762939453,
                    -0.0,
                    -179.99998474121094
                ],
                "scale": [
                    1.0,
                    1.0,
                    1.0
                ]
            }
        },
        {
            "type": "MESH",
            "name": "WarpRoot.008",
            "file_name": "WarpRoot",
            "ModelFileType": "obj",
            "DrawType": "Instancing",
            "InstancingObjName": "WarpRoot",
            "transform": {
                "translate": [
                    15.126625061035156,
                    7.979964256286621,
                    38.545066833496094
                ],
                "rotate": [
                    0.0,
                    -0.0,
                    -179.99998474121094
                ],
                "scale": [
                    1.0,
                    1.0,
                    1.0
                ]
            }
        },
        {
            "type": "MESH",
            "name": "WarpRoot.009",
            "file_name": "WarpRoot",
            "ModelFileType": "obj",
            "DrawType": "Instancing",
            "InstancingObjName": "WarpRoot",
            "transform": {
                "translate": [
                    15.126625061035156,
                    2.9799644947052,
                    38.545066833496094
                ],
                "rotate": [
                    0.0,
                    -0.0,
                    -179.99998474121094
                ],
                "scale": [
                    1.0,
                    1.0,
                    1.0
                ]
            }
        },
        {
            "type": "MESH",
            "name": "WarpRootConnector.002",
            "file_name": "WarpRootConnector",
            "ModelFileType": "obj",
            "DrawType": "Instancing",
            "InstancingObjName": "WarpConnector",
            "transform": {
                "translate": [
                    15.126625061035156,
                    11.979964256286621,
                    5.045070648193359
                ],
                "rotate": [
                    0.0,
                    -0.0,
                    -179.99998474121094
                ],
                "scale": [
                    1.0,
                    1.0,
                    1.0
                ]
            }
        },
        {
            "type": "MESH",
            "name": "StageCoin.001",
            "file_name": "StageCoin",
            "ModelFileType": "gltf",
            "DrawType": "Normal",
            "transform": {
                "translate": [
                    -48.626792907714844,
                    0.0,
                    3.1435084342956543
                ],
                "rotate": [
                    0.0,
                    -0.0,
                    0.0
                ],
                "scale": [
                    1.0,
                    1.0,
                    1.0
                ]
            }
        },
        {
            "type": "MESH",
            "name": "StageCoin",
            "file_name": "StageCoin",
            "ModelFileType": "gltf",
            "DrawType": "Normal",
            "transform": {
                "translate": [
                    -42.5374870300293,
                    0.0,
                    12.931659698486328
                ],
                "rotate": [
                    0.0,
                    -0.0,
                    0.0
                ],
                "scale": [
                    1.0,
                    1.0,
                    1.0
                ]
            }
        },
        {
            "type": "MESH",
            "name": "StageCoin.002",
            "file_name": "StageCoin",
            "ModelFileType": "gltf",
            "DrawType": "Normal",
            "transform": {
                "translate": [
                    49.38435363769531,
                    0.0,
                    34.30961990356445
                ],
                "rotate": [
                    0.0,
                    -0.0,
                    0.0
                ],
                "scale": [
                    1.0,
                    1.0,
                    1.0
                ]
            }
        },
        {
            "type": "MESH",
            "name": "GunEnemyCore",
            "file_name": "GunEnemyCore",
            "ModelFileType": "obj",
            "DrawType": "Normal",
            "transform": {
                "translate": [
                    38.552490234375,
                    0.0,
                    33.559715270996094
                ],
                "rotate": [
                    0.0,
                    -0.0,
                    90.00000762939453
                ],
                "scale": [
                    2.0,
                    2.0,
                    2.0
                ]
            },
            "collider": {
                "type": "Box",
                "center": [
                    0.0,
                    0.0,
                    0.0
                ],
                "size": [
                    2.0,
                    2.0,
                    2.0
                ]
            },
            "children": [
                {
                    "type": "MESH",
                    "name": "GunEnemyBarrel",
                    "file_name": "GunEnemyBarrel",
                    "ModelFileType": "obj",
                    "DrawType": "Normal",
                    "transform": {
                        "translate": [
                            0.0,
                            1.1100006103515625,
                            0.0048675537109375
                        ],
                        "rotate": [
                            0.0,
                            -0.0,
                            0.0
                        ],
                        "scale": [
                            1.0,
                            1.0,
                            1.0
                        ]
                    }
                },
                {
                    "type": "MESH",
                    "name": "GunEnemyLeft",
                    "file_name": "GunEnemyLeft",
                    "ModelFileType": "obj",
                    "DrawType": "Normal",
                    "transform": {
                        "translate": [
                            0.0,
                            0.0,
                            -0.6382675170898438
                        ],
                        "rotate": [
                            0.0,
                            -0.0,
                            0.0
                        ],
                        "scale": [
                            1.0,
                            1.0,
                            1.0
                        ]
                    }
                },
                {
                    "type": "MESH",
                    "name": "GunEnemyRight",
                    "file_name": "GunEnemyRight",
                    "ModelFileType": "obj",
                    "DrawType": "Normal",
                    "transform": {
                        "translate": [
                            0.0,
                            0.0,
                            -0.6382675170898438
                        ],
                        "rotate": [
                            0.0,
                            -0.0,
                            0.0
                        ],
                        "scale": [
                            1.0,
                            1.0,
                            1.0
                        ]
                    }
                }
            ]
        }
    ]
}